kling/__init__.py
kling/__main__.py
kling/kling.py
kling_creator-0.4.0.dist-info/licenses/LICENSE
kling_creator-0.4.0.dist-info/METADATA
kling_creator-0.4.0.dist-info/WHEEL
kling_creator-0.4.0.dist-info/entry_points.txt
kling_creator-0.4.0.dist-info/top_level.txt
kling_creator-0.4.0.dist-info/RECORD
