Metadata-Version: 2.4
Name: kling-creator
Version: 0.4.0
Summary: High quality video generation by https://klingai.kuaishou.com/. Reverse engineered API.
Home-page: https://github.com/yihong0618/klingCreator
Author: yihong0618
Author-email: zouzou0208@gmail.com
Classifier: Intended Audience :: Developers
Classifier: Topic :: Software Development :: Libraries :: Python Modules
Classifier: Programming Language :: Python :: 3.9
Classifier: Programming Language :: Python :: 3.10
Classifier: Programming Language :: Python :: 3.11
Classifier: Programming Language :: Python :: 3.12
Classifier: Programming Language :: Python :: 3.13
License-File: LICENSE
Requires-Dist: requests
Requires-Dist: fake-useragent>=2.0.3
Requires-Dist: rich
Dynamic: author
Dynamic: author-email
Dynamic: classifier
Dynamic: home-page
Dynamic: license-file
Dynamic: requires-dist
Dynamic: summary
